README.md
setup.py
gluonfr/__init__.py
gluonfr/loss.py
gluonfr.egg-info/PKG-INFO
gluonfr.egg-info/SOURCES.txt
gluonfr.egg-info/dependency_links.txt
gluonfr.egg-info/requires.txt
gluonfr.egg-info/top_level.txt
gluonfr.egg-info/zip-safe
gluonfr/data/__init__.py
gluonfr/data/dataset.py
gluonfr/metrics/__init__.py
gluonfr/metrics/verification.py
gluonfr/model_zoo/__init__.py
gluonfr/model_zoo/attention_net.py
gluonfr/model_zoo/mobile_facenet.py
gluonfr/model_zoo/se_resnet.py
gluonfr/nn/__init__.py
gluonfr/nn/basic_blocks.py
gluonfr/utils/__init__.py
gluonfr/utils/lr_scheduler.py
gluonfr/utils/viz.py