Metadata-Version: 2.1
Name: gluonfr
Version: 1.0.2
Summary: Gluon FR Toolkit
Home-page: https://github.com/THUFutureLab/gluon-face
Author: haoxintong
Author-email: haoxintongpku@gmail.com
License: MIT
Platform: UNKNOWN
